metrixify/__init__.py
metrixify/evaluator.py
metrixify-0.5.0.dist-info/LICENSE
metrixify-0.5.0.dist-info/METADATA
metrixify-0.5.0.dist-info/WHEEL
metrixify-0.5.0.dist-info/top_level.txt
metrixify-0.5.0.dist-info/RECORD
