Metadata-Version: 2.2
Name: metrixify
Version: 0.5.0
Summary: A Python library for automatic model evaluation
Home-page: https://github.com/susmitsekhar/metrixify
Author: Susmit Sekhar Panda
Author-email: susmit.vssut@gmail.com
Classifier: Programming Language :: Python :: 3
Classifier: License :: OSI Approved :: MIT License
Classifier: Operating System :: OS Independent
Requires-Python: >=3.7
License-File: LICENSE
Requires-Dist: numpy>=1.21.0
Requires-Dist: scikit-learn>=1.0.0
Dynamic: author
Dynamic: author-email
Dynamic: classifier
Dynamic: description
Dynamic: description-content-type
Dynamic: home-page
Dynamic: requires-dist
Dynamic: requires-python
Dynamic: summary
